psmb_client/__init__.py
psmb_client/guardian.py
psmb_client/stream.py
psmb_client-0.3.2.dist-info/LICENSE
psmb_client-0.3.2.dist-info/METADATA
psmb_client-0.3.2.dist-info/WHEEL
psmb_client-0.3.2.dist-info/top_level.txt
psmb_client-0.3.2.dist-info/RECORD
